nendo_plugin_import_core/__init__.py
nendo_plugin_import_core/config.py
nendo_plugin_import_core/plugin.py
nendo_plugin_import_core-0.1.0.dist-info/METADATA
nendo_plugin_import_core-0.1.0.dist-info/WHEEL
nendo_plugin_import_core-0.1.0.dist-info/RECORD
