Metadata-Version: 2.1
Name: nendo-plugin-import-core
Version: 0.1.0
Summary: A plugin for importing NendoTracks and NendoCollections from the web. Works with youtube links and direct downloads currently.
Home-page: https://nendo.ai
License: MIT
Keywords: AI,generative,music,okio,nendo,music retrieval,web crawling
Author: Aaron Abebe
Author-email: aaron@okio.ai
Requires-Python: >=3.8,<3.11
Classifier: Development Status :: 3 - Alpha
Classifier: Intended Audience :: Developers
Classifier: License :: OSI Approved :: MIT License
Classifier: Operating System :: OS Independent
Classifier: Programming Language :: Python :: 3
Classifier: Programming Language :: Python :: 3.8
Classifier: Programming Language :: Python :: 3.9
Classifier: Programming Language :: Python :: 3.10
Classifier: Topic :: Multimedia :: Sound/Audio
Requires-Dist: nendo (>=0.2.1,<0.3.0)
Requires-Dist: pydantic (>=2.4.2,<3.0.0)
Requires-Dist: requests (>=2.31.0,<3.0.0)
Requires-Dist: tqdm (>=4.65.0,<5.0.0)
Requires-Dist: yt_dlp (>=2023.11.16,<2024.0.0)
Project-URL: Repository, https://github.com/okio-ai/nendo_plugin_import_core
